pytessy/__init__.py
pytessy/pytessy.py
pytessy-0.1.0.dist-info/LICENSE
pytessy-0.1.0.dist-info/METADATA
pytessy-0.1.0.dist-info/WHEEL
pytessy-0.1.0.dist-info/top_level.txt
pytessy-0.1.0.dist-info/RECORD
