Metadata-Version: 2.1
Name: pytessy
Version: 0.1.0
Summary: Tesseract-OCR, faster
Home-page: https://github.com/hyperrixel/pytessy
Author: rixel
Author-email: python@hyperrixel.com
License: UNKNOWN
Project-URL: Documentation, https://pytessy.readthedocs.io/
Project-URL: Source, https://github.com/hyperrixel/pytessy
Project-URL: Projects, https://hyperrixel.github.io/
Project-URL: Homepage, https://www.hyperrixel.com/
Keywords: tesseract Tesseract-OCR
Platform: UNKNOWN
Classifier: Programming Language :: Python :: 3
Classifier: License :: OSI Approved :: Boost Software License 1.0 (BSL-1.0)
Classifier: Operating System :: OS Independent
Requires-Python: >=3.6
